bonkprice/__init__.py
bonkprice-0.0.1.dist-info/METADATA
bonkprice-0.0.1.dist-info/WHEEL
bonkprice-0.0.1.dist-info/top_level.txt
bonkprice-0.0.1.dist-info/RECORD
