Metadata-Version: 2.2
Name: bonkprice
Version: 0.0.1
Summary: A Bonk Blockchain python lib for market data and price view and more ...
Author-email: RibbitX <mail@ribbitx.com>
License: MIT
Requires-Dist: requests
